{
  "$schema": "http://json-schema.org/draft-04/schema#",
  "id": "http://justice.gov.uk/core/courts/progression.event.court-application-hearing-deleted.json",
  "type": "object",
  "properties": {
    "seedingHearingId": {
      "$ref": "http://justice.gov.uk/core/courts/courtsDefinitions.json#/definitions/uuid"
    },
    "applicationId": {
      "$ref": "http://justice.gov.uk/core/courts/courtsDefinitions.json#/definitions/uuid"
    },
    "hearingId": {
      "$ref": "http://justice.gov.uk/core/courts/courtsDefinitions.json#/definitions/uuid"
    }
  },
  "required": [
    "seedingHearingId",
    "applicationId",
    "hearingId"
  ],
  "additionalProperties": false
}
