{
  "$schema": "http://json-schema.org/draft-04/schema#",
  "id": "http://justice.gov.uk/progression/courts/public.progression.boxwork-application-referred.json",
  "type": "object",
  "properties": {
    "hearingId": {
      "$ref": "http://justice.gov.uk/domain/core/common/definitions.json#/definitions/uuid"
    },
    "applicationId": {
      "$ref": "http://justice.gov.uk/domain/core/common/definitions.json#/definitions/uuid"
    },
    "caseId": {
      "type": "object",
      "$ref": "http://justice.gov.uk/domain/core/common/definitions.json#/definitions/uuid"
    },
    "dueDate": {
      "description": "The date by which the application must be resulted and concluded",
      "$ref": "courtsDefinitions.json#/definitions/datePattern"
    }
  },
  "required": [
    "applicationId",
    "hearingId",
    "dueDate"
  ],
  "additionalProperties": false
}