{
  "$schema": "http://json-schema.org/draft-04/schema#",
  "description": "Command schema for notifying court register document to the court center",
  "id": "http://justice.gov.uk/progression/courts/record-nows-document-generated.json",
  "type": "object",
  "properties": {
    "materialId": {
      "description": "The court centre reference data identifier",
      "$ref": "http://justice.gov.uk/domain/core/common/definitions.json#/definitions/uuid"
    },
    "systemDocGeneratorId": {
      "description": "The document file id",
      "$ref": "http://justice.gov.uk/domain/core/common/definitions.json#/definitions/uuid"
    },
    "payloadFileId": {
      "description": "The payload file id",
      "$ref": "http://justice.gov.uk/domain/core/common/definitions.json#/definitions/uuid"
    }
  },
  "additionalProperties": false,
  "required": [
    "materialId",
    "systemDocGeneratorId",
    "payloadFileId"
  ]
}